pycontour/__init__.py
pycontour/coor_transform.py
pycontour/cv2_transform.py
pycontour/poly_transform.py
pycontour/setup.py
pycontour/cnt/__init__.py
pycontour/cnt/cnt_property.py
pycontour/cnt/setup.py
pycontour/fea/__init__.py
pycontour/fea/setup.py
pycontour/fea/zernike.py
pycontour/img/__init__.py
pycontour/img/mask.py
pycontour/img/setup.py
pycontour/poly/__init__.py
pycontour/poly/adjust.py
pycontour/poly/poly_property.py
pycontour/poly/setup.py
pycontour/rela/__init__.py
pycontour/rela/intersect.py
pycontour/rela/overlap.py
pycontour/rela/point.py
pycontour/rela/setup.py
pycontour/transform/__init__.py
pycontour/transform/rotate.py
pycontour/transform/setup.py
pycontour/transform/shift.py
pycontour/transform/smooth.py
pycontour-1.5.1.dist-info/LICENSE
pycontour-1.5.1.dist-info/METADATA
pycontour-1.5.1.dist-info/WHEEL
pycontour-1.5.1.dist-info/top_level.txt
pycontour-1.5.1.dist-info/RECORD
