Metadata-Version: 2.1
Name: pycontour
Version: 1.5.1
Summary: pycontour: A Python Toolkit for 2D Contour Processing
Home-page: https://github.com/PingjunChen/pycontour
Author: Pingjun Chen
Author-email: pingjunchen@ieee.org
License: BSD 3-Clause
Platform: UNKNOWN
Classifier: Development Status :: 3 - Alpha
Classifier: Intended Audience :: Developers
Classifier: Intended Audience :: Healthcare Industry
Classifier: Intended Audience :: Information Technology
Classifier: Intended Audience :: Science/Research
Classifier: License :: OSI Approved :: BSD License
Classifier: Programming Language :: Python :: 3
Classifier: Programming Language :: Python :: 3.7
Classifier: Programming Language :: Python :: 3.8
Classifier: Topic :: Scientific/Engineering
Classifier: Topic :: Scientific/Engineering :: Mathematics
Classifier: Topic :: Scientific/Engineering :: Artificial Intelligence
Requires-Dist: numpy (>=1.16.0)
Requires-Dist: scikit-image (>=0.14.5)
Requires-Dist: opencv-python (==4.2.0.32)
Requires-Dist: shapely (>=1.6.4)
Requires-Dist: mahotas (>=1.4.8)
